flask_server_status/__init__.py
flask_server_status/handler_logs.py
flask_server_status/main.py
flask_server_status/db/__init__.py
flask_server_status/db/engine.py
flask_server_status/db/models.py
flask_server_status/db/schemas.py
flask_server_status/routes/__init__.py
flask_server_status/routes/configure.py
flask_server_status/statsig/static/index.css
flask_server_status/statsig/static/index.js
flask_server_status/statsig/static/logo.png
flask_server_status/statsig/templates/index.html
flask_server_status/utils/__init__.py
flask_server_status/utils/cache.py
flask_server_status/utils/cron.py
flask_server_status/utils/logs.py
flask_server_status-0.0.4.dist-info/LICENSE
flask_server_status-0.0.4.dist-info/METADATA
flask_server_status-0.0.4.dist-info/WHEEL
flask_server_status-0.0.4.dist-info/top_level.txt
flask_server_status-0.0.4.dist-info/RECORD
