Metadata-Version: 2.1
Name: flask-server-status
Version: 0.0.4
Summary: It is a Flask extension to view incidents caused by the server
Home-page: https://github.com/fcoagz/flask-status/
Author: Francisco Griman
Author-email: grihardware@gmail.com
License: MIT
Platform: any
Classifier: Intended Audience :: Developers
Classifier: Programming Language :: Python :: 3
Classifier: Programming Language :: Python :: 3.12
License-File: LICENSE
Requires-Dist: setuptools ==75.1.0
Requires-Dist: flask >=3.0.0
Requires-Dist: cachetools >=5.5.0
Requires-Dist: apscheduler ==3.10.4
Requires-Dist: sqlalchemy ==2.0.35
Requires-Dist: marshmallow ==3.22.0
